LICENSE
MANIFEST.in
README.md
pyproject.toml
setup.py
SimpleStereo.egg-info/PKG-INFO
SimpleStereo.egg-info/SOURCES.txt
SimpleStereo.egg-info/dependency_links.txt
SimpleStereo.egg-info/requires.txt
SimpleStereo.egg-info/top_level.txt
simplestereo/__init__.py
simplestereo/_passive.cpp
simplestereo/_rigs.py
simplestereo/_unwrapping.cpp
simplestereo/active.py
simplestereo/calibration.py
simplestereo/passive.py
simplestereo/points.py
simplestereo/rectification.py
simplestereo/unwrapping.py
simplestereo/utils.py
simplestereo/headers/colorconversion.hpp
simplestereo/headers/safequeue.hpp