Metadata-Version: 2.2
Name: SimpleStereo
Version: 1.0.9
Summary: Stereo vision made simple
Home-page: https://github.com/decadenza/SimpleStereo
Author: decadenza
Project-URL: Homepage, https://github.com/decadenza/SimpleStereo
Project-URL: Bug Tracker, https://github.com/decadenza/SimpleStereo/issues
Classifier: Programming Language :: Python :: 3
Classifier: License :: OSI Approved :: GNU General Public License v3 (GPLv3)
Classifier: Operating System :: OS Independent
Requires-Python: >=3.7
License-File: LICENSE
Requires-Dist: numpy<2,>=1.19
Requires-Dist: opencv-contrib-python>=4.5
Requires-Dist: scipy>=1.4
Requires-Dist: matplotlib>=3
Dynamic: home-page
